nonebot_plugin_groupmate_waifu/__init__.py
nonebot_plugin_groupmate_waifu/config.py
nonebot_plugin_groupmate_waifu-1.6.1.dist-info/LICENSE
nonebot_plugin_groupmate_waifu-1.6.1.dist-info/METADATA
nonebot_plugin_groupmate_waifu-1.6.1.dist-info/WHEEL
nonebot_plugin_groupmate_waifu-1.6.1.dist-info/RECORD
