Metadata-Version: 2.3
Name: nonebot-plugin-groupmate-waifu
Version: 1.6.1
Summary: 
Author: KarisAya
Author-email: karisaya@foxmail.com
Requires-Python: >=3.12,<4.0.0
Classifier: Programming Language :: Python :: 3
Classifier: Programming Language :: Python :: 3.12
Classifier: Programming Language :: Python :: 3.13
Requires-Dist: clovers (>=0.4.6,<0.5)
Requires-Dist: clovers-apscheduler (>=0.2.2,<0.3.0)
Requires-Dist: clovers-groupmate-waifu (>=0.2.5,<1.0.0)
Requires-Dist: nonebot-plugin-clovers (>=0.3.4,<0.4)
Requires-Dist: nonebot2 (>=2.4.2,<3.0.0)
Requires-Dist: pydantic (>=2.11.4,<3.0.0)
